geoland/__init__.py
geoland-0.0.0.dist-info/LICENSE
geoland-0.0.0.dist-info/METADATA
geoland-0.0.0.dist-info/WHEEL
geoland-0.0.0.dist-info/RECORD
