Metadata-Version: 2.1
Name: geoland
Version: 0.0.0
Summary: hosting cloud-platform CLI for OneCode-based Python scripts
License: MIT
Keywords: onecode,workflow,CLI,cloud
Author: DeepLime
Author-email: support@deeplime.io
Requires-Python: >=3.7,<4
Classifier: Development Status :: 1 - Planning
Classifier: Intended Audience :: Developers
Classifier: License :: OSI Approved :: MIT License
Classifier: Natural Language :: English
Classifier: Operating System :: Microsoft :: Windows
Classifier: Operating System :: Unix
Classifier: Programming Language :: Python
Classifier: Programming Language :: Python :: 3
Classifier: Programming Language :: Python :: 3.7
Classifier: Programming Language :: Python :: 3.8
Classifier: Programming Language :: Python :: 3.9
Classifier: Programming Language :: Python :: 3.10
Classifier: Programming Language :: Python :: 3.11
Classifier: Topic :: Scientific/Engineering
